{"aHQwn5CcKhJQYWqHZSv1xA==":"zgnr-logo-green-90x90.png","DV7lz4XyjGAhxGEy3dcIEQ==":"mekanism-506x159.jpg","VwHsTrs8Tkv9ko5/uDYRsg==":"projecte-506x159.jpg","mYqZpDwudy4kmeFsifo1cw==":"thaumcraft-506x159.jpg","DZdmRb1xHcZA/oNew8lACA==":"botania-506x159.jpg","d4/m9OaVUkp82+YLkYw+sg==":"gold-506x159.png","zRuZiosJ8n4Zbi4sDcTFdg==":"agricraft-506x159.png","haNW04blYCoVU17HeuvLAA==":"mysitcal-506x159.png","/RVcsqoW0Mxx9O3tuU8p8Q==":"forestry-506x159.jpg","ajABx1vhi9nuUSQhvqhRMQ==":"enderio-506x159.jpg","1AmPD6uHTy7cbc2PQ66yOw==":"techreborn-506x159.jpg","BbVXlfmn0LtnGW5d9LBA6Q==":"extreme-506x159.jpg","Xkha5RatP5Kbao8GnWSpag==":"buildcraft-506x159.jpg","mLGG8yjrZZ4jnmKRrnFTaQ==":"pic%201-900x506.jpg","ArhCNlEutWpC17FKQ/weYQ==":"pic%202-900x506.jpg","I7CW1WxT0+IQjkhGj4R4gQ==":"pic%203-900x506.jpg","bNWC9JPNaJ0sl4LmXIV8tw==":"pic%204-900x506.jpg"}